Nsc512/__init__.py
Nsc512/core.py
Nsc512/main.py
nsc410-1.0.0.dist-info/METADATA
nsc410-1.0.0.dist-info/WHEEL
nsc410-1.0.0.dist-info/entry_points.txt
nsc410-1.0.0.dist-info/top_level.txt
nsc410-1.0.0.dist-info/RECORD
